jusho/__about__.py
jusho/__init__.py
jusho/jusho.py
jusho/models.py
jusho/organize_data.py
jusho/data/address.db
jusho/gateway/__init__.py
jusho/gateway/addresses.py
jusho/gateway/cities.py
jusho/gateway/insert.py
jusho/gateway/prefectures.py
jusho/gateway/utils.py
jusho-1.0.1.dist-info/METADATA
jusho-1.0.1.dist-info/WHEEL
jusho-1.0.1.dist-info/licenses/LICENSE
jusho-1.0.1.dist-info/RECORD
