Metadata-Version: 2.3
Name: jusho
Version: 1.0.1
Summary: Easy wrapper for the zip code data of Japan
Project-URL: Homepage, https://github.com/nagataaaas/Jusho
Project-URL: Documentation, https://github.com/nagataaaas/Jusho
Project-URL: Repository, https://github.com/nagataaaas/Jusho.git
Project-URL: Issues, https://github.com/nagataaaas/Jusho/issues
Project-URL: Changelog, https://github.com/nagataaaas/Jusho/blob/master/CHANGELOG.md
Author-email: nagataaaas <nagata@nagata.pro>
License: MIT License
License-File: LICENSE
Keywords: address,japan
Classifier: Development Status :: 4 - Beta
Classifier: Environment :: Other Environment
Classifier: Intended Audience :: Developers
Classifier: License :: OSI Approved :: MIT License
Classifier: Operating System :: OS Independent
Classifier: Programming Language :: Python
Classifier: Programming Language :: Python :: 3
Classifier: Topic :: Software Development :: Libraries :: Python Modules
Requires-Python: >=3.6
